ribosor/__init__.py
ribosor/readingframes.py
ribosor/ribosor.py
RiBoSor-1.0.dist-info/LICENSE
RiBoSor-1.0.dist-info/METADATA
RiBoSor-1.0.dist-info/WHEEL
RiBoSor-1.0.dist-info/entry_points.txt
RiBoSor-1.0.dist-info/top_level.txt
RiBoSor-1.0.dist-info/RECORD
