Metadata-Version: 2.1
Name: RiBoSor
Version: 1.0
Summary: Creates overlapping reading frames within an existing gene
Home-page: https://github.com/afrenoy/RiBoSor
Author: Antoine Frenoy
Author-email: antoine.frenoy@pasteur.fr
License: UNKNOWN
Platform: UNKNOWN
Classifier: Programming Language :: Python :: 3
Classifier: License :: OSI Approved :: GNU General Public License v3 (GPLv3)
Classifier: Topic :: Scientific/Engineering :: Bio-Informatics
Requires-Dist: biopython
